{"DOI": "10.1021/Ja800550a", "adsorbate": "methanol", "adsorbent_basis": "mass", "adsorbent_unit": "g", "articleSource": "UNKNOWN", "compositionType": "molefraction", "concentrationUnits": "", "date": "1000-01-01", "digitizer": "UNKNOWN", "filename": "10.1021Ja800550a.Isotherm5", "henry_slope": 52.696602141199676, "henry_virial": 28.91278788730077, "iso_ref": "", "iso_type": "blank", "isotherm_data": [{"loading": "0.0317166", "pressure": "0.00251131"}, {"loading": "0.222016", "pressure": "0.00450973"}, {"loading": "0.348882", "pressure": "0.0055069"}, {"loading": "1.3321", "pressure": "0.00695157"}, {"loading": "0.983214", "pressure": "0.00697404"}, {"loading": "2.02986", "pressure": "0.00791195"}, {"loading": "2.56904", "pressure": "0.00888256"}, {"loading": "3.04479", "pressure": "0.00935458"}, {"loading": "3.74256", "pressure": "0.00981229"}, {"loading": "3.96457", "pressure": "0.0108033"}, {"loading": "4.28174", "pressure": "0.0112856"}, {"loading": "4.44032", "pressure": "0.013286"}, {"loading": "4.66234", "pressure": "0.0152824"}, {"loading": "4.7892", "pressure": "0.0182903"}, {"loading": "4.91607", "pressure": "0.0223035"}, {"loading": "5.01122", "pressure": "0.0298374"}, {"loading": "5.07465", "pressure": "0.0383787"}, {"loading": "5.07465", "pressure": "0.0479294"}, {"loading": "5.13809", "pressure": "0.0579788"}, {"loading": "5.13809", "pressure": "0.0670268"}, {"loading": "5.1698", "pressure": "0.0770782"}, {"loading": "5.1698", "pressure": "0.0861263"}, {"loading": "5.20152", "pressure": "0.0961776"}, {"loading": "5.20152", "pressure": "0.105226"}, {"loading": "5.20152", "pressure": "0.114776"}, {"loading": "5.20152", "pressure": "0.134381"}, {"loading": "5.20152", "pressure": "0.143429"}, {"loading": "5.20152", "pressure": "0.152477"}, {"loading": "5.26495", "pressure": "0.161521"}], "loading_basis": "molar", "loading_unit": "mmol", "material": "C6H10CuN3", "material_batch": "NIST-MATDB-c8ef237d84290dbc0b2948cb057d6671", "pressure_mode": "absolute", "pressure_unit": "bar", "temperature": 298.0, "volloaded": {}}