{"DOI": "10.1039/C0cc05199c", "adsorbate": "carbon dioxide", "adsorbent_basis": "mass", "adsorbent_unit": "g", "articleSource": "UNKNOWN", "compositionType": "molefraction", "concentrationUnits": "", "date": "1000-01-01", "digitizer": "UNKNOWN", "filename": "10.1039C0cc05199c.Isotherm9", "henry_slope": 2.731037675681659, "henry_virial": 2.3090443320585803, "iso_ref": "", "iso_type": "blank", "isotherm_data": [{"loading": "0.024735709680000002", "pressure": "0.0131837"}, {"loading": "0.1241683662", "pressure": "0.046115"}, {"loading": "0.2113148934", "pressure": "0.0691539"}, {"loading": "0.2609493177", "pressure": "0.0889201"}, {"loading": "0.34801420860000004", "pressure": "0.11526"}, {"loading": "0.497080308", "pressure": "0.167957"}, {"loading": "0.646229382", "pressure": "0.217354"}, {"loading": "0.795463215", "pressure": "0.263451"}, {"loading": "0.9194656320000001", "pressure": "0.316167"}, {"loading": "1.0560837570000001", "pressure": "0.365573"}, {"loading": "1.2051525330000001", "pressure": "0.41827"}, {"loading": "1.3167890580000001", "pressure": "0.464395"}, {"loading": "1.453326885", "pressure": "0.517101"}, {"loading": "1.5773293019999999", "pressure": "0.569818"}, {"loading": "1.6889658270000003", "pressure": "0.615942"}, {"loading": "1.8255839520000001", "pressure": "0.665348"}, {"loading": "1.924528932", "pressure": "0.718083"}, {"loading": "2.023469451", "pressure": "0.770817"}, {"loading": "2.1350256780000003", "pressure": "0.820242"}, {"loading": "2.2340509560000004", "pressure": "0.869676"}, {"loading": "2.333076234", "pressure": "0.91911"}, {"loading": "2.4194858040000002", "pressure": "0.971854"}, {"loading": "2.518676139", "pressure": "1.01469"}], "loading_basis": "molar", "loading_unit": "mmol", "material": "SNU-21S", "material_batch": "NIST-MATDB-5b2f2fe36d08c935b34cbe0368bb90af", "pressure_mode": "absolute", "pressure_unit": "bar", "temperature": 298.0, "uptake": {"0": 0.0, "0.5": 1.4090257925337344, "1.0": 2.4846602173184706}, "volloaded": {"0": 0, "0.5": 1.4090257925337344, "1.0": 2.4846602173184706}}