{"DOI": "10.1002/ejic.201100790", "adsorbate": "ethanol", "adsorbent_basis": "mass", "adsorbent_unit": "g", "articleSource": "UNKNOWN", "compositionType": "molefraction", "concentrationUnits": "", "date": "1000-01-01", "digitizer": "UNKNOWN", "filename": "10.1002ejic.201100790.Isotherm4", "henry_slope": 0.22565179739917124, "henry_virial": 0.1798924668850199, "iso_ref": "", "iso_type": "blank", "isotherm_data": [{"loading": "0.0001068637011", "pressure": "0.000763264"}, {"loading": "0.0003514143828", "pressure": "0.00139932"}, {"loading": "0.00041159193450000006", "pressure": "0.00521564"}, {"loading": "0.0005327504640000001", "pressure": "0.00979522"}, {"loading": "0.0005779002450000001", "pressure": "0.0125939"}, {"loading": "0.000759900123", "pressure": "0.0184456"}, {"loading": "0.001125742272", "pressure": "0.0231523"}, {"loading": "0.001201548045", "pressure": "0.0256966"}, {"loading": "0.0013380992550000002", "pressure": "0.0298945"}, {"loading": "0.001995244704", "pressure": "0.0319299"}, {"loading": "0.002024798829", "pressure": "0.0358734"}, {"loading": "0.002222929683", "pressure": "0.0385448"}, {"loading": "0.0024054648810000003", "pressure": "0.0423612"}, {"loading": "0.0024352866660000004", "pressure": "0.045287"}, {"loading": "0.0025260546330000003", "pressure": "0.0491033"}, {"loading": "0.0029080946730000003", "pressure": "0.0503754"}, {"loading": "0.0032281491180000004", "pressure": "0.0547006"}, {"loading": "0.0039617338020000005", "pressure": "0.0568632"}, {"loading": "0.004343738154", "pressure": "0.0582625"}], "loading_basis": "molar", "loading_unit": "mmol", "material": "C40H84Cu10N24O50", "material_batch": "NIST-MATDB-ba1f506e482d7024a4ca8b2a0cfd21b5", "pressure_mode": "absolute", "pressure_unit": "bar", "temperature": 293.0, "uptake": {"0": 0.0}, "volloaded": {"0": 0}}