{"DOI": "10.1016/j.micromeso.2014.02.014", "adsorbate": "carbon dioxide", "adsorbent_basis": "mass", "adsorbent_unit": "g", "articleSource": "UNKNOWN", "compositionType": "molefraction", "concentrationUnits": "", "date": "1000-01-01", "digitizer": "UNKNOWN", "filename": "10.1016j.micromeso.2014.02.014.Isotherm2", "iso_ref": "", "iso_type": "blank", "isotherm_data": [{"loading": "-0.0309858", "pressure": "0.0451467"}, {"loading": "0.248728", "pressure": "0.180587"}, {"loading": "0.870056", "pressure": "0.316027"}, {"loading": "1.21195", "pressure": "0.496614"}, {"loading": "1.5849", "pressure": "0.677201"}, {"loading": "1.86476", "pressure": "0.902935"}, {"loading": "2.20679", "pressure": "1.17381"}, {"loading": "2.42446", "pressure": "1.3544"}, {"loading": "2.76657", "pressure": "1.67043"}, {"loading": "3.01537", "pressure": "1.89616"}, {"loading": "3.10881", "pressure": "2.07675"}, {"loading": "3.88725", "pressure": "3.386"}, {"loading": "4.51047", "pressure": "4.74041"}, {"loading": "5.50776", "pressure": "6.99774"}, {"loading": "5.85148", "pressure": "8.35214"}, {"loading": "6.35104", "pressure": "10.0677"}, {"loading": "6.97692", "pressure": "13.1377"}, {"loading": "7.16613", "pressure": "14.9887"}, {"loading": "7.3552", "pressure": "16.7494"}, {"loading": "7.51279", "pressure": "18.2393"}], "loading_basis": "molar", "loading_unit": "mmol", "material_batch": "NIST-MATDB-5ab0dbe0639729711750ef4b97715f0f", "material_name": "UiO-66", "pressure_mode": "absolute", "pressure_unit": "bar", "t_iso": 303.0, "volloaded": 1.7371434730257738}