{"DOI": "10.1039/c4ee02717e", "adsorbate": "carbon dioxide", "adsorbent_basis": "mass", "adsorbent_unit": "g", "articleSource": "Figure 2a", "compositionType": "molefraction", "concentrationUnits": "", "date": "2016-07-08", "digitizer": "Adithya Varadan", "filename": "10.1039c4ee02717e.Isotherm1", "henry_slope": 627.7635705828428, "henry_virial": 2558.5380289637883, "iso_ref": "", "iso_type": "exp", "isotherm_data": [{"loading": "0.0", "pressure": "0.0"}, {"loading": "2.60208", "pressure": "0.004145"}, {"loading": "1.46713", "pressure": "0.004497"}, {"loading": "1.79931", "pressure": "0.009344"}, {"loading": "2.87889", "pressure": "0.013961"}, {"loading": "2.10381", "pressure": "0.016676"}, {"loading": "2.32526", "pressure": "0.024033"}, {"loading": "2.82353", "pressure": "0.048631"}, {"loading": "3.87543", "pressure": "0.058207"}, {"loading": "3.21107", "pressure": "0.075739"}, {"loading": "3.51557", "pressure": "0.102873"}, {"loading": "4.56747", "pressure": "0.105022"}, {"loading": "3.76471", "pressure": "0.132499"}, {"loading": "4.0692", "pressure": "0.152206"}, {"loading": "5.06574", "pressure": "0.154373"}, {"loading": "4.26298", "pressure": "0.184325"}, {"loading": "4.51211", "pressure": "0.206525"}, {"loading": "5.45329", "pressure": "0.208709"}, {"loading": "5.78547", "pressure": "0.260586"}, {"loading": "4.81661", "pressure": "0.260886"}, {"loading": "6.06228", "pressure": "0.317431"}, {"loading": "5.14879", "pressure": "0.317714"}, {"loading": "6.25606", "pressure": "0.366876"}, {"loading": "5.37024", "pressure": "0.369626"}, {"loading": "6.44983", "pressure": "0.421272"}, {"loading": "5.64706", "pressure": "0.423995"}, {"loading": "6.58824", "pressure": "0.468259"}, {"loading": "5.86851", "pressure": "0.470957"}, {"loading": "6.72664", "pressure": "0.525146"}, {"loading": "6.0346", "pressure": "0.525361"}, {"loading": "6.83737", "pressure": "0.577092"}, {"loading": "6.20069", "pressure": "0.577289"}, {"loading": "6.92042", "pressure": "0.631522"}, {"loading": "6.3391", "pressure": "0.634177"}, {"loading": "7.03114", "pressure": "0.683468"}, {"loading": "6.50519", "pressure": "0.686106"}, {"loading": "7.08651", "pressure": "0.737906"}, {"loading": "6.67128", "pressure": "0.74051"}, {"loading": "7.14187", "pressure": "0.789869"}, {"loading": "6.75433", "pressure": "0.792465"}, {"loading": "7.14187", "pressure": "0.826998"}, {"loading": "6.83737", "pressure": "0.839469"}, {"loading": "7.14187", "pressure": "0.876503"}, {"loading": "7.00346", "pressure": "0.896348"}, {"loading": "7.11419", "pressure": "0.926017"}, {"loading": "7.08651", "pressure": "0.948302"}, {"loading": "7.16955", "pressure": "0.997782"}], "loading_basis": "molar", "loading_unit": "mmol", "material": "[MnIIMnIII(OH)Cl2(bbta)]", "material_batch": "NIST-MATDB-8153e78fa83dd7aac27ea34942a5f24f", "pressure_mode": "absolute", "pressure_unit": "bar", "temperature": 298.0, "uptake": {"0": 0.0, "0.5": 6.3284311941537945}, "volloaded": {"0": 0, "0.5": 6.3284311941537945}}