{"DOI": "10.1021/je000273+", "adsorbate": "ammonia", "adsorbent_basis": "mass", "adsorbent_unit": "g", "articleSource": "UNKNOWN", "compositionType": "molefraction", "concentrationUnits": "", "date": "1000-01-01", "digitizer": "UNKNOWN", "filename": "10.1021je000273plus.Isotherm50", "henryc": 1799.428669729996, "iso_ref": "", "iso_type": "blank", "isotherm_data": [{"loading": "5.12626", "pressure": "0.00258398"}, {"loading": "6.17245", "pressure": "0.0232558"}, {"loading": "6.64129", "pressure": "0.0361757"}, {"loading": "7.00156", "pressure": "0.0568475"}, {"loading": "7.61266", "pressure": "0.129199"}, {"loading": "7.72013", "pressure": "0.152455"}, {"loading": "7.7914", "pressure": "0.178295"}, {"loading": "7.89886", "pressure": "0.20155"}, {"loading": "7.97013", "pressure": "0.22739"}, {"loading": "8.00539", "pressure": "0.250646"}, {"loading": "8.07675", "pressure": "0.273902"}, {"loading": "8.11192", "pressure": "0.299742"}, {"loading": "8.18319", "pressure": "0.325581"}, {"loading": "8.18235", "pressure": "0.348837"}, {"loading": "8.21761", "pressure": "0.372093"}, {"loading": "8.28786", "pressure": "0.426357"}, {"loading": "8.32303", "pressure": "0.452196"}, {"loading": "8.35829", "pressure": "0.475452"}, {"loading": "8.39346", "pressure": "0.501292"}, {"loading": "8.39252", "pressure": "0.527132"}, {"loading": "8.42788", "pressure": "0.547804"}, {"loading": "8.46305", "pressure": "0.573643"}, {"loading": "8.46221", "pressure": "0.596899"}, {"loading": "8.46127", "pressure": "0.622739"}, {"loading": "8.49644", "pressure": "0.648579"}, {"loading": "8.49569", "pressure": "0.669251"}, {"loading": "8.53086", "pressure": "0.69509"}, {"loading": "8.5651", "pressure": "0.74677"}, {"loading": "8.60027", "pressure": "0.77261"}, {"loading": "8.59952", "pressure": "0.793282"}, {"loading": "8.59859", "pressure": "0.819121"}, {"loading": "8.59775", "pressure": "0.842377"}, {"loading": "8.63301", "pressure": "0.865633"}, {"loading": "8.63208", "pressure": "0.891473"}, {"loading": "8.63114", "pressure": "0.917313"}, {"loading": "8.66631", "pressure": "0.943152"}, {"loading": "8.70017", "pressure": "1.00517"}], "loading_basis": "molar", "loading_unit": "mmol", "material_batch": "NIST-MATDB-2f8e4d6eabff4483bae71358b48e8359", "material_name": "Zeolite 4A TG242", "pressure_mode": "absolute", "pressure_unit": "bar", "t_iso": 298.0, "volloaded": {"0.5": 8.3917015, "1.0": 8.697347332387372}}