{"DOI": "10.1039/C2ta00616b", "adsorbate": "nitrogen", "adsorbent_basis": "mass", "adsorbent_unit": "g", "articleSource": "UNKNOWN", "compositionType": "molefraction", "concentrationUnits": "", "date": "1000-01-01", "digitizer": "UNKNOWN", "filename": "10.1039C2ta00616b.isotherm11", "henry_slope": 0.4882403421200729, "henry_virial": 0.12143853744542372, "iso_ref": "", "iso_type": "blank", "isotherm_data": [{"loading": "0.008020674332499925", "pressure": "0.0164278"}, {"loading": "0.008020674332499925", "pressure": "0.271184"}, {"loading": "0.05481682390049362", "pressure": "0.463453"}, {"loading": "0.07353531228537118", "pressure": "0.569201"}, {"loading": "0.09225380067024876", "pressure": "0.710999"}, {"loading": "0.09225380067024876", "pressure": "0.869621"}, {"loading": "0.11097228905512632", "pressure": "0.968159"}], "loading_basis": "molar", "loading_unit": "mmol", "material": "PAF-18-OH", "material_batch": "NIST-MATDB-5b4d9a8ad9c3397a31f52ff67c0dae1d", "pressure_mode": "absolute", "pressure_unit": "bar", "temperature": 298.0, "volloaded": {"0.5": 0.06128602043378144}}