{"DOI": "10.1039/C4ra07030e", "adsorbate": "carbon dioxide", "adsorbent_basis": "mass", "adsorbent_unit": "g", "articleSource": "UNKNOWN", "compositionType": "molefraction", "concentrationUnits": "", "date": "1000-01-01", "digitizer": "UNKNOWN", "filename": "10.1039C4ra07030e.Isotherm3", "iso_ref": "", "iso_type": "blank", "isotherm_data": [{"loading": "0.335766", "pressure": "0.042735"}, {"loading": "1.06569", "pressure": "1.00427"}, {"loading": "1.38686", "pressure": "1.98718"}, {"loading": "1.89781", "pressure": "2.99145"}, {"loading": "2.08759", "pressure": "3.97436"}, {"loading": "2.37956", "pressure": "4.97863"}, {"loading": "2.51095", "pressure": "5.96154"}, {"loading": "2.70073", "pressure": "6.98718"}, {"loading": "2.87591", "pressure": "7.99145"}, {"loading": "3.12409", "pressure": "8.95299"}, {"loading": "3.22628", "pressure": "9.95726"}], "loading_basis": "molar", "loading_unit": "mmol", "material_batch": "NIST-MATDB-1b5c20248717ca46ef341e3c5f2c1f30", "material_name": "NH2-MIL-53(Al)", "pressure_mode": "absolute", "pressure_unit": "bar", "t_iso": 303.0, "volloaded": 0.9106238032624918}