{"DOI": "10.1039/C2jm30866e", "adsorbate": "carbon dioxide", "adsorbent_basis": "mass", "adsorbent_unit": "g", "articleSource": "UNKNOWN", "compositionType": "molefraction", "concentrationUnits": "", "date": "1000-01-01", "digitizer": "UNKNOWN", "filename": "10.1039C2jm30866e.isotherm2", "henry_slope": 3.1004747598155027, "henry_virial": 5.55797839522434, "iso_ref": "", "iso_type": "blank", "isotherm_data": [{"loading": "0.013736221980000003", "pressure": "0.0025126"}, {"loading": "0.1602560718", "pressure": "0.0446858"}, {"loading": "0.3205116975", "pressure": "0.106362"}, {"loading": "0.47618944500000004", "pressure": "0.182573"}, {"loading": "0.5860772580000001", "pressure": "0.253644"}, {"loading": "0.7600696410000001", "pressure": "0.371231"}, {"loading": "0.860803482", "pressure": "0.478654"}, {"loading": "0.9569558760000001", "pressure": "0.595756"}, {"loading": "1.0073205660000002", "pressure": "0.698011"}, {"loading": "1.0576897170000001", "pressure": "0.785703"}, {"loading": "1.112631393", "pressure": "0.90255"}, {"loading": "1.121789826", "pressure": "1.00212"}], "loading_basis": "molar", "loading_unit": "mmol", "material": "Ca-5TIA-MOF", "material_batch": "NIST-MATDB-0a23b582e4d401abdfedb870e167ce84", "pressure_mode": "absolute", "pressure_unit": "bar", "temperature": 298.0, "uptake": {"0": 0.0, "0.5": 0.8783306719909822, "1.0": 1.1215948287321484}, "volloaded": {"0": 0, "0.5": 0.8783306719909822, "1.0": 1.1215948287321484}}