{"DOI": "10.1039/B704977c", "adsorbate": "carbon dioxide", "adsorbent_basis": "mass", "adsorbent_unit": "g", "articleSource": "UNKNOWN", "compositionType": "molefraction", "concentrationUnits": "", "date": "1000-01-01", "digitizer": "UNKNOWN", "filename": "10.1039B704977c.Isotherm2", "henry_slope": 5.376593490032739, "henry_virial": 9.164233241974417, "iso_ref": "", "iso_type": "blank", "isotherm_data": [{"loading": "0.0314714628", "pressure": "0.00585345"}, {"loading": "0.04008217422", "pressure": "0.0177418"}, {"loading": "0.05445988800000001", "pressure": "0.0474865"}, {"loading": "0.0659701602", "pressure": "0.0742615"}, {"loading": "0.07462896120000001", "pressure": "0.104025"}, {"loading": "0.08898267480000001", "pressure": "0.124832"}, {"loading": "0.100492947", "pressure": "0.151607"}, {"loading": "0.1091437182", "pressure": "0.178392"}, {"loading": "0.11779448940000002", "pressure": "0.205176"}, {"loading": "0.1292967318", "pressure": "0.228972"}, {"loading": "0.1379550867", "pressure": "0.258736"}, {"loading": "0.1494492993", "pressure": "0.279552"}, {"loading": "0.15810007050000002", "pressure": "0.306337"}, {"loading": "0.1667508417", "pressure": "0.333122"}, {"loading": "0.17540161290000003", "pressure": "0.359906"}, {"loading": "0.184051938", "pressure": "0.386691"}, {"loading": "0.19270270920000002", "pressure": "0.413475"}, {"loading": "0.19848594960000004", "pressure": "0.43729"}, {"loading": "0.2099962218", "pressure": "0.464065"}, {"loading": "0.218646993", "pressure": "0.49085"}, {"loading": "0.22728928830000003", "pressure": "0.514655"}, {"loading": "0.23594005950000002", "pressure": "0.541439"}, {"loading": "0.2532416019", "pressure": "0.595009"}, {"loading": "0.2590243962", "pressure": "0.618823"}, {"loading": "0.26481566640000004", "pressure": "0.645617"}, {"loading": "0.2734664376", "pressure": "0.672402"}, {"loading": "0.2821167627", "pressure": "0.699187"}, {"loading": "0.2879000031", "pressure": "0.723001"}, {"loading": "0.2965588041", "pressure": "0.752765"}, {"loading": "0.30233356860000005", "pressure": "0.773601"}, {"loading": "0.3081248388", "pressure": "0.800395"}, {"loading": "0.31392369270000003", "pressure": "0.830168"}, {"loading": "0.31970693310000003", "pressure": "0.853983"}, {"loading": "0.3254982033", "pressure": "0.880777"}, {"loading": "0.3312809976", "pressure": "0.904592"}, {"loading": "0.3371360601", "pressure": "0.95522"}, {"loading": "0.3429273303", "pressure": "0.982014"}, {"loading": "0.3429991524", "pressure": "1.00883"}], "loading_basis": "molar", "loading_unit": "mmol", "material": "C35H30N2O8Rh2", "material_batch": "NIST-MATDB-7c22b74caa04ae0cdc275c66491546f8", "pressure_mode": "absolute", "pressure_unit": "bar", "temperature": 293.0, "volloaded": {"0.5": 0.22196885823818527, "1.0": 0.3429755027452044}}