{"DOI": "10.1039/C2cc16877d", "adsorbate": "carbon dioxide", "adsorbent_basis": "mass", "adsorbent_unit": "g", "articleSource": "UNKNOWN", "compositionType": "molefraction", "concentrationUnits": "", "date": "1000-01-01", "digitizer": "UNKNOWN", "filename": "10.1039C2cc16877d.Isotherm4", "iso_ref": "", "iso_type": "blank", "isotherm_data": [{"loading": "0.134842", "pressure": "0.0229098"}, {"loading": "0.23854", "pressure": "0.0432741"}, {"loading": "0.311093", "pressure": "0.0610928"}, {"loading": "0.404377", "pressure": "0.0840026"}, {"loading": "0.487245", "pressure": "0.109458"}, {"loading": "0.642445", "pressure": "0.175642"}, {"loading": "0.699389", "pressure": "0.196006"}, {"loading": "0.82859", "pressure": "0.264736"}, {"loading": "0.895775", "pressure": "0.300373"}, {"loading": "0.962861", "pressure": "0.346193"}, {"loading": "1.02478", "pressure": "0.389467"}, {"loading": "1.13815", "pressure": "0.483652"}, {"loading": "1.19487", "pressure": "0.526926"}, {"loading": "1.2979", "pressure": "0.616019"}, {"loading": "1.34408", "pressure": "0.674567"}, {"loading": "1.38524", "pressure": "0.715295"}, {"loading": "1.4573", "pressure": "0.784025"}, {"loading": "1.47775", "pressure": "0.817117"}, {"loading": "1.49826", "pressure": "0.845117"}, {"loading": "1.52881", "pressure": "0.908756"}, {"loading": "1.55439", "pressure": "0.949484"}, {"loading": "1.58489", "pressure": "1.01821"}, {"loading": "1.61046", "pressure": "1.05894"}], "loading_basis": "molar", "loading_unit": "mmol", "material_batch": "NIST-MATDB-224db38a05d106fe89ac3ed2852c23ae", "material_name": "C48H55N4O19Zn3@FCNF", "pressure_mode": "absolute", "pressure_unit": "bar", "t_iso": 298.0, "volloaded": 1.4671721367702164}