{"DOI": "10.1166/jnn.2010.1395", "adsorbate": "propene", "adsorbent_basis": "mass", "adsorbent_unit": "g", "articleSource": "UNKNOWN", "compositionType": "molefraction", "concentrationUnits": "", "date": "1000-01-01", "digitizer": "UNKNOWN", "filename": "10.1166jnn.2010.1395.Isotherm26", "henry_slope": 0.03251171128089153, "henry_virial": 0.0, "iso_ref": "", "iso_type": "blank", "isotherm_data": [{"loading": "0.00497625", "pressure": "0.153061"}, {"loading": "0.00531091", "pressure": "0.280612"}, {"loading": "0.0055714", "pressure": "0.433673"}, {"loading": "0.00575791", "pressure": "0.663265"}, {"loading": "0.00587016", "pressure": "0.892857"}, {"loading": "0.00594537", "pressure": "1.14796"}, {"loading": "0.00598345", "pressure": "1.40306"}, {"loading": "0.00605857", "pressure": "1.63265"}, {"loading": "0.00609664", "pressure": "1.88776"}, {"loading": "0.00613472", "pressure": "2.14286"}, {"loading": "0.00617271", "pressure": "2.37245"}, {"loading": "0.00617366", "pressure": "2.62755"}, {"loading": "0.0061746", "pressure": "2.88265"}, {"loading": "0.00621268", "pressure": "3.13776"}, {"loading": "0.00621363", "pressure": "3.39286"}, {"loading": "0.00621458", "pressure": "3.64796"}, {"loading": "0.00625266", "pressure": "3.90306"}, {"loading": "0.0062536", "pressure": "4.15816"}, {"loading": "0.00625455", "pressure": "4.41327"}, {"loading": "0.0062555", "pressure": "4.66837"}, {"loading": "0.00625644", "pressure": "4.92347"}, {"loading": "0.00625739", "pressure": "5.17857"}, {"loading": "0.00625834", "pressure": "5.43367"}, {"loading": "0.00625929", "pressure": "5.68878"}, {"loading": "0.00626023", "pressure": "5.94388"}, {"loading": "0.00626118", "pressure": "6.19898"}, {"loading": "0.00626213", "pressure": "6.45408"}, {"loading": "0.00626307", "pressure": "6.70918"}, {"loading": "0.00622689", "pressure": "6.96429"}, {"loading": "0.00622784", "pressure": "7.21939"}, {"loading": "0.00622878", "pressure": "7.47449"}, {"loading": "0.00622973", "pressure": "7.72959"}, {"loading": "0.00623068", "pressure": "7.98469"}, {"loading": "0.00623163", "pressure": "8.2398"}, {"loading": "0.00619535", "pressure": "8.46939"}, {"loading": "0.00619629", "pressure": "8.72449"}, {"loading": "0.00619724", "pressure": "8.97959"}, {"loading": "0.00616106", "pressure": "9.23469"}, {"loading": "0.006162", "pressure": "9.4898"}, {"loading": "0.00616295", "pressure": "9.7449"}, {"loading": "0.0061639", "pressure": "10.0"}, {"loading": "0.00616485", "pressure": "10.2551"}], "loading_basis": "molar", "loading_unit": "mmol", "material": "Carbon Nanotube", "material_batch": "NIST-MATDB-5eeb37664de08b731baed19524bb8469", "pressure_mode": "absolute", "pressure_unit": "bar", "temperature": 298.0, "volloaded": {"0.5": 0.005625281009660615, "1.0": 0.005901748123346256, "1.5": 0.006015167987717235, "2.0": 0.006113394602900823, "2.5": 0.0061731849999999994, "3.0": 0.006192116710438634, "3.5": 0.006214028992551941, "4.0": 0.006253017207369659, "4.5": 0.006254872985103881, "5.0": 0.006256725, "5.5": 0.006258587005213438, "6.0": 0.006260438992551941, "6.5": 0.0062622992073696595, "7.0": 0.006227022985103881, "7.5": 0.006228875, "8.0": 0.006230737012661205, "8.5": 0.00619546279263034, "9.0": 0.00619434531634653, "9.5": 0.006162037985103881, "10.0": 0.0061639}}