{"DOI": "10.1007/s10904-014-0131-z", "adsorbate": "carbon dioxide", "adsorbent_basis": "mass", "adsorbent_unit": "g", "articleSource": "Figure 5b", "compositionType": "molefraction", "concentrationUnits": "", "date": "2016-07-08", "digitizer": "Adithya Varadan", "filename": "10.1007s109040140131z.Isotherm14", "henry_slope": 2.310667620847113, "henry_virial": 3.7007505569608052, "iso_ref": "", "iso_type": "exp", "isotherm_data": [{"loading": "0.084734", "pressure": "0.010714"}, {"loading": "0.188535", "pressure": "0.050703"}, {"loading": "0.103965", "pressure": "0.058608"}, {"loading": "0.292336", "pressure": "0.090692"}, {"loading": "0.207789", "pressure": "0.101257"}, {"loading": "0.28333", "pressure": "0.135901"}, {"loading": "0.377398", "pressure": "0.138645"}, {"loading": "0.452962", "pressure": "0.175948"}, {"loading": "0.368345", "pressure": "0.178533"}, {"loading": "0.462718", "pressure": "0.215854"}, {"loading": "0.566191", "pressure": "0.218606"}, {"loading": "0.651183", "pressure": "0.258577"}, {"loading": "0.547757", "pressure": "0.261145"}, {"loading": "0.642154", "pressure": "0.301126"}, {"loading": "0.745626", "pressure": "0.303878"}, {"loading": "0.727192", "pressure": "0.346418"}, {"loading": "0.830642", "pressure": "0.34651"}, {"loading": "0.821565", "pressure": "0.383739"}, {"loading": "0.91561", "pressure": "0.383823"}, {"loading": "0.915985", "pressure": "0.42638"}, {"loading": "1.00063", "pressure": "0.426454"}, {"loading": "1.02919", "pressure": "0.466378"}, {"loading": "1.12324", "pressure": "0.46646"}, {"loading": "1.23646", "pressure": "0.509118"}, {"loading": "1.12366", "pressure": "0.514338"}, {"loading": "1.21805", "pressure": "0.554318"}, {"loading": "1.30269", "pressure": "0.554393"}, {"loading": "1.38764", "pressure": "0.589046"}, {"loading": "1.3219", "pressure": "0.599627"}, {"loading": "1.41625", "pressure": "0.634288"}, {"loading": "1.51977", "pressure": "0.642359"}, {"loading": "1.5295", "pressure": "0.679604"}, {"loading": "1.61417", "pressure": "0.68234"}, {"loading": "1.72737", "pressure": "0.722337"}, {"loading": "1.63335", "pressure": "0.724914"}, {"loading": "1.75594", "pressure": "0.762259"}, {"loading": "1.81236", "pressure": "0.762309"}, {"loading": "1.89738", "pressure": "0.804942"}, {"loading": "1.85038", "pressure": "0.807559"}, {"loading": "1.98239", "pressure": "0.847573"}, {"loading": "1.95423", "pressure": "0.852869"}, {"loading": "2.04846", "pressure": "0.874229"}, {"loading": "2.0392", "pressure": "0.89018"}, {"loading": "2.13343", "pressure": "0.911542"}, {"loading": "2.15243", "pressure": "0.932838"}, {"loading": "2.23728", "pressure": "0.956851"}, {"loading": "2.23744", "pressure": "0.975469"}, {"loading": "2.34127", "pressure": "1.01812"}], "loading_basis": "molar", "loading_unit": "mmol", "material": "ZIF-8-90 100%", "material_batch": "NIST-MATDB-9b4ce3b98af846393c4e66dbcf5d86f1", "pressure_mode": "absolute", "pressure_unit": "bar", "temperature": 298.0, "uptake": {"0": 0.0, "0.5": 1.2122596164845985, "1.0": 2.2971584996834777}, "volloaded": {"0": 0, "0.5": 1.2122596164845985, "1.0": 2.2971584996834777}}