{"DOI": "10.1039/C2ta00155a", "adsorbate": "methane", "adsorbent_basis": "mass", "adsorbent_unit": "g", "articleSource": "UNKNOWN", "compositionType": "molefraction", "concentrationUnits": "", "date": "1000-01-01", "digitizer": "UNKNOWN", "filename": "10.1039C2ta00155a.isotherm7", "henry_slope": 1.1184892788033602, "henry_virial": 0.7561273824048249, "iso_ref": "", "iso_type": "blank", "isotherm_data": [{"loading": "0.00873441495", "pressure": "0.0117765"}, {"loading": "0.15142373790000002", "pressure": "0.121374"}, {"loading": "0.2839207911", "pressure": "0.260198"}, {"loading": "0.4469922", "pressure": "0.459909"}, {"loading": "0.5591060520000001", "pressure": "0.601168"}, {"loading": "0.6712199040000001", "pressure": "0.744862"}, {"loading": "0.752758062", "pressure": "0.88125"}, {"loading": "0.8037160650000001", "pressure": "0.988412"}, {"loading": "0.8241028350000001", "pressure": "1.04686"}], "loading_basis": "molar", "loading_unit": "mmol", "material": "UTSA-50a", "material_batch": "NIST-MATDB-8d3db4b0d98c04559d08b18dabab1a76", "pressure_mode": "absolute", "pressure_unit": "bar", "temperature": 296.0, "uptake": {"0": 0.0, "0.5": 0.4788114571130477, "1.0": 0.8077579807329593}, "volloaded": {"0": 0, "0.5": 0.4788114571130477, "1.0": 0.8077579807329593}}