{"DOI": "10.1038/Nchem.834", "adsorbate": "carbon dioxide", "adsorbent_basis": "mass", "adsorbent_unit": "g", "articleSource": "UNKNOWN", "compositionType": "molefraction", "concentrationUnits": "", "date": "1000-01-01", "digitizer": "UNKNOWN", "filename": "10.1038Nchem.834.isotherm18", "iso_ref": "", "iso_type": "blank", "isotherm_data": [{"loading": "1.0992665270008046", "pressure": "0.946953"}, {"loading": "4.822653136346904", "pressure": "3.6562"}, {"loading": "8.918377270517022", "pressure": "7.93855"}, {"loading": "15.992824325491144", "pressure": "15.0175"}, {"loading": "22.198464887365997", "pressure": "20.0864"}, {"loading": "30.389822266858747", "pressure": "25.1554"}, {"loading": "37.71250948652346", "pressure": "29.9621"}, {"loading": "43.17356588759776", "pressure": "35.1184"}, {"loading": "45.78003081131929", "pressure": "40.0125"}], "loading_basis": "molar", "loading_unit": "mmol", "material_batch": "NIST-MATDB-ba976b9f5157eb8a13e8ece7180bc3d9", "material_name": "NU-100SP", "pressure_mode": "absolute", "pressure_unit": "bar", "t_iso": 298.0, "volloaded": 0.9493861499185416}