{"DOI": "10.1007/s11224-012-0120-1", "adsorbate": "acetylene", "adsorbent_basis": "mass", "adsorbent_unit": "g", "articleSource": "UNKNOWN", "compositionType": "molefraction", "concentrationUnits": "", "date": "1000-01-01", "digitizer": "UNKNOWN", "filename": "10.1007s11224-012-0120-1.isotherm31", "henry_slope": 8952988.018084086, "henry_virial": 5672932.182743764, "iso_ref": "", "iso_type": "blank", "isotherm_data": [{"loading": "10.02734658", "pressure": "1.12e-06"}, {"loading": "10.74186495", "pressure": "2.1e-06"}, {"loading": "12.030603240000001", "pressure": "1.06e-05"}, {"loading": "12.42616011", "pressure": "2.08e-05"}, {"loading": "12.974818500000001", "pressure": "5.37e-05"}, {"loading": "13.42140921", "pressure": "0.000101"}, {"loading": "13.70213994", "pressure": "0.000206"}, {"loading": "13.982826060000002", "pressure": "0.000521"}, {"loading": "14.097696810000002", "pressure": "0.00104008"}, {"loading": "14.199764490000002", "pressure": "0.00505286"}, {"loading": "14.212522950000002", "pressure": "0.0102908"}, {"loading": "14.26355679", "pressure": "0.0197523"}, {"loading": "14.659113660000001", "pressure": "0.0998268"}, {"loading": "15.131221290000003", "pressure": "0.191609"}, {"loading": "15.705396600000002", "pressure": "0.284467"}, {"loading": "16.611336480000002", "pressure": "0.484971"}, {"loading": "18.117013200000002", "pressure": "0.96838"}], "loading_basis": "molar", "loading_unit": "mmol", "material": "COF-105", "material_batch": "NIST-MATDB-1733c0f5ae26290495f099f06d0dd880", "pressure_mode": "absolute", "pressure_unit": "bar", "temperature": 298.0, "uptake": {"0": 0.0, "0.5": 16.658147390481354}, "volloaded": {"0": 0, "0.5": 16.658147390481354}}