{"DOI": "10.1016/j.ijggc.2011.10.007", "adsorbate": "carbon dioxide", "adsorbent_basis": "mass", "adsorbent_unit": "g", "articleSource": "UNKNOWN", "compositionType": "molefraction", "concentrationUnits": "", "date": "1000-01-01", "digitizer": "UNKNOWN", "filename": "10.1016j.ijggc.2011.10.007.isotherm1", "henry_slope": 3.583943416040811, "henry_virial": 5.047461286266613, "iso_ref": "", "iso_type": "blank", "isotherm_data": [{"loading": "0.072738", "pressure": "0.011236"}, {"loading": "0.399445", "pressure": "0.11236"}, {"loading": "1.30976", "pressure": "0.162921"}, {"loading": "2.07426", "pressure": "0.219101"}, {"loading": "2.61973", "pressure": "0.308989"}, {"loading": "3.00123", "pressure": "0.398876"}, {"loading": "3.34574", "pressure": "0.533708"}, {"loading": "3.58081", "pressure": "0.679775"}, {"loading": "3.76102", "pressure": "0.842697"}, {"loading": "3.90465", "pressure": "1.01685"}, {"loading": "3.97637", "pressure": "1.11236"}], "loading_basis": "molar", "loading_unit": "mmol", "material": "Zeolite X", "material_batch": "NIST-MATDB-499290019152654e4f76dc66546b6475", "pressure_mode": "absolute", "pressure_unit": "bar", "temperature": 308.0, "volloaded": {"0.5": 3.2596125000000002, "1.0": 3.8907532224538195}}