{"DOI": "10.1039/C4dt02300e", "adsorbate": "carbon dioxide", "adsorbent_basis": "mass", "adsorbent_unit": "g", "articleSource": "UNKNOWN", "compositionType": "molefraction", "concentrationUnits": "", "date": "1000-01-01", "digitizer": "UNKNOWN", "filename": "10.1039C4dt02300e.Isotherm13", "iso_ref": "", "iso_type": "blank", "isotherm_data": [{"loading": "0.10814534640000002", "pressure": "9.40758"}, {"loading": "0.15771196350000002", "pressure": "13.6115"}, {"loading": "0.2117846367", "pressure": "18.4148"}, {"loading": "0.27486986820000003", "pressure": "23.4213"}, {"loading": "0.34246070970000003", "pressure": "29.6246"}, {"loading": "0.41906366340000006", "pressure": "35.832"}, {"loading": "0.48665495100000006", "pressure": "42.0353"}, {"loading": "0.558753633", "pressure": "48.6389"}, {"loading": "0.626342244", "pressure": "55.0413"}, {"loading": "0.702946536", "pressure": "61.4478"}], "loading_basis": "molar", "loading_unit": "mmol", "material_batch": "NIST-MATDB-c72a7787d6aa9690e6f0e608535eba56", "material_name": "MOF-205", "pressure_mode": "absolute", "pressure_unit": "bar", "t_iso": 298.0, "volloaded": 0.00916903701349734}