{"DOI": "10.1021/Jp308525k", "adsorbate": "carbon dioxide", "adsorbent_basis": "mass", "adsorbent_unit": "g", "articleSource": "UNKNOWN", "compositionType": "molefraction", "concentrationUnits": "", "date": "1000-01-01", "digitizer": "UNKNOWN", "filename": "10.1021Jp308525k.isotherm22", "iso_ref": "", "iso_type": "blank", "isotherm_data": [{"loading": "0.0965554", "pressure": "0.0259382"}, {"loading": "0.559922", "pressure": "1.09855"}, {"loading": "0.868833", "pressure": "1.48468"}, {"loading": "1.89854", "pressure": "3.02924"}, {"loading": "3.13418", "pressure": "5.00284"}, {"loading": "3.61471", "pressure": "5.98963"}, {"loading": "4.43847", "pressure": "7.96323"}, {"loading": "5.09061", "pressure": "9.89392"}, {"loading": "6.01735", "pressure": "13.7124"}, {"loading": "6.58368", "pressure": "17.5738"}, {"loading": "6.85827", "pressure": "19.4187"}, {"loading": "7.16718", "pressure": "23.1943"}, {"loading": "7.27015", "pressure": "24.9962"}, {"loading": "7.47609", "pressure": "26.7982"}, {"loading": "7.5619", "pressure": "28.6431"}], "loading_basis": "molar", "loading_unit": "mmol", "material_batch": "NIST-MATDB-88982b60a6735e027ce761e7a7181713", "material_name": "MIL-47(V)", "pressure_mode": "absolute", "pressure_unit": "bar", "t_iso": 303.0, "volloaded": 0.4309488725087679}