{"DOI": "10.1007/s10450-014-9620-1", "adsorbate": "methane", "adsorbent_basis": "mass", "adsorbent_unit": "g", "articleSource": "UNKNOWN", "compositionType": "molefraction", "concentrationUnits": "", "date": "1000-01-01", "digitizer": "UNKNOWN", "filename": "10.1007s10450-014-9620-1.Isotherm2", "iso_ref": "", "iso_type": "blank", "isotherm_data": [{"loading": "2.775107836537263", "pressure": "1.70404"}, {"loading": "3.0597401949784326", "pressure": "2.15247"}, {"loading": "3.3443663200937492", "pressure": "2.42152"}, {"loading": "3.8424589223826264", "pressure": "2.95964"}, {"loading": "4.198244695439699", "pressure": "3.58744"}, {"loading": "4.55403046849677", "pressure": "4.12556"}, {"loading": "4.980969656169746", "pressure": "4.84305"}, {"loading": "5.336749195900965", "pressure": "5.47085"}, {"loading": "5.763694616899793", "pressure": "6.27803"}, {"loading": "5.906007679457451", "pressure": "6.81614"}, {"loading": "6.190633804572768", "pressure": "7.62332"}, {"loading": "6.546425810955694", "pressure": "8.43049"}, {"loading": "6.831039469419303", "pressure": "9.23767"}, {"loading": "7.044530879896278", "pressure": "10.1345"}, {"loading": "7.471451367591691", "pressure": "11.3004"}, {"loading": "7.613758196823498", "pressure": "12.1973"}, {"loading": "7.82724960730047", "pressure": "13.0045"}, {"loading": "7.969556436532276", "pressure": "13.8117"}, {"loading": "8.18304784700925", "pressure": "14.7085"}, {"loading": "8.325354676241055", "pressure": "15.3363"}, {"loading": "8.46766150547286", "pressure": "16.1435"}, {"loading": "8.609968334704666", "pressure": "17.0404"}, {"loading": "8.75227516393647", "pressure": "17.9372"}, {"loading": "8.894581993168273", "pressure": "18.7444"}, {"loading": "9.108073403645248", "pressure": "19.5516"}, {"loading": "9.179195651631884", "pressure": "20.4484"}, {"loading": "9.321502480863689", "pressure": "21.3453"}, {"loading": "9.392687062108859", "pressure": "22.1525"}, {"loading": "9.534993891340664", "pressure": "23.0493"}, {"loading": "9.606178472585833", "pressure": "23.9462"}, {"loading": "9.677300720572468", "pressure": "24.7534"}, {"loading": "9.819607549804275", "pressure": "25.6502"}, {"loading": "9.890792131049443", "pressure": "26.5471"}, {"loading": "10.104221208267882", "pressure": "27.4439"}, {"loading": "10.104221208267882", "pressure": "28.4305"}, {"loading": "10.104221208267882", "pressure": "28.6099"}, {"loading": "10.246590370758222", "pressure": "29.5067"}, {"loading": "10.317712618744856", "pressure": "30.3139"}, {"loading": "10.317712618744856", "pressure": "31.2108"}, {"loading": "10.388897199990026", "pressure": "32.1076"}, {"loading": "10.460019447976663", "pressure": "33.0045"}, {"loading": "10.531204029221831", "pressure": "33.9013"}], "loading_basis": "molar", "loading_unit": "mmol", "material_batch": "NIST-MATDB-73875395ea6add86b0f24072ddc472e5", "material_name": "Zn4O", "pressure_mode": "absolute", "pressure_unit": "bar", "t_iso": 298.0}