{"DOI": "10.1021/Ja4045289", "adsorbate": "methane", "adsorbent_basis": "mass", "adsorbent_unit": "g", "articleSource": "UNKNOWN", "compositionType": "molefraction", "concentrationUnits": "", "date": "1000-01-01", "digitizer": "UNKNOWN", "filename": "10.1021Ja4045289.isotherm11", "iso_ref": "", "iso_type": "blank", "isotherm_data": [{"loading": "0.03341088255000001", "pressure": "0.280697"}, {"loading": "2.216675361", "pressure": "3.49246"}, {"loading": "3.815140881", "pressure": "6.85717"}, {"loading": "5.5695585", "pressure": "11.9042"}, {"loading": "6.544242390000001", "pressure": "16.0336"}, {"loading": "7.440903390000001", "pressure": "21.9983"}, {"loading": "8.5325547", "pressure": "34.2336"}, {"loading": "9.429260310000002", "pressure": "46.4689"}, {"loading": "10.0140528", "pressure": "61.4572"}, {"loading": "10.286976780000002", "pressure": "66.5042"}], "loading_basis": "molar", "loading_unit": "mmol", "material_batch": "NIST-MATDB-491f2d4553a5f70eb3e8a54f967be37f", "material_name": "PCN-14", "pressure_mode": "absolute", "pressure_unit": "bar", "t_iso": 298.0}